{
    "list": [
      {
        "mainchapterid": 1,
        "subchapterlist": [
          {
            "subchapterid": 105,
            "progressRewardList": [
              {
                "type": "NORMALCLEAR_ONETHIRD",
                "rewardList": [
                  {
                    "type": "ITEM",
                    "id": 2,
                    "num": 130
                  }
                ]
              },
              {
                "type": "NORMALCLEAR_TWOTHIRD",
                "rewardList": [
                  {
                    "type": "ITEM",
                    "id": 2,
                    "num": 130
                  }
                ]
              },
              {
                "type": "NORMALCLEAR_ALLCLEAR",
                "rewardList": [
                  {
                    "type": "ITEM",
                    "id": 2,
                    "num": 130
                  }
                ]
              },
              {
                "type": "EXCLEAR_ALLCLEAR",
                "rewardList": [
                  {
                    "type": "ITEM",
                    "id": 2,
                    "num": 260
                  }
                ]
              }
            ],
            "excludedNodeIdList": [
              10528,
              10531,
              10536
            ]
          }
        ]
      },
      {
        "mainchapterid": 91,
        "subchapterlist": [
          {
            "subchapterid": 9105,
            "progressRewardList": [
              {
                "type": "NORMALCLEAR_ONETHIRD",
                "rewardList": [
                  {
                    "type": "ITEM",
                    "id": 2,
                    "num": 130
                  }
                ]
              },
              {
                "type": "NORMALCLEAR_TWOTHIRD",
                "rewardList": [
                  {
                    "type": "ITEM",
                    "id": 2,
                    "num": 130
                  }
                ]
              },
              {
                "type": "NORMALCLEAR_ALLCLEAR",
                "rewardList": [
                  {
                    "type": "ITEM",
                    "id": 2,
                    "num": 130
                  }
                ]
              },
              {
                "type": "EXCLEAR_ALLCLEAR",
                "rewardList": [
                  {
                    "type": "ITEM",
                    "id": 2,
                    "num": 260
                  }
                ]
              }
            ],
            "excludedNodeIdList": [
              910513
            ]
          },
          {
            "subchapterid": 9107,
            "progressRewardList": [
              {
                "type": "NORMALCLEAR_ONETHIRD",
                "rewardList": [
                  {
                    "type": "ITEM",
                    "id": 2,
                    "num": 130
                  }
                ]
              },
              {
                "type": "NORMALCLEAR_TWOTHIRD",
                "rewardList": [
                  {
                    "type": "ITEM",
                    "id": 2,
                    "num": 130
                  }
                ]
              },
              {
                "type": "NORMALCLEAR_ALLCLEAR",
                "rewardList": [
                  {
                    "type": "ITEM",
                    "id": 2,
                    "num": 130
                  }
                ]
              },
              {
                "type": "EXCLEAR_ALLCLEAR",
                "rewardList": [
                  {
                    "type": "ITEM",
                    "id": 2,
                    "num": 260
                  }
                ]
              }
            ],
            "excludedNodeIdList": [
              
            ]
          }
        ]
      }
    ]
  }