{"dataList":[{"id":0,"characterlist":"다친이스마엘:5","feeling":"angry4","bg":"story_depths_heart","bgm":"Bad_Time","soundeffect":"SFX_Heart_Near:loop","voice":"S503V-1118"},{"id":1,"feeling":"angry3","voice":"S503V-1119"},{"id":2,"characterlist":"에이해브:5","feeling":"idle2","soundeffect":"SFX_Big_Bell_1","voice":"S503V-1120"},{"id":3,"voice":"S503V-1121"},{"id":4,"characterlist":"에이해브:5:mode=FADE_OUT","feeling":"shouting3","bg":"white","cg":"white:FadeOut","effect":"WhiteFadeIn:4","soundeffect":"SFX_Big_Bell_2","voice":"S503V-1122"},{"id":5,"characterlist":"에이해브그림자:5:mode=FADE_IN","bg":"story_depths_heart_gaslight","effect":"CustomCamShake:[20][30][2]","soundeffect":"SFX_Sweat_Crumble_Hard:delay=0.7, SFX_Big_Bell_3","voice":"S503V-1123"}]}