{"dataList":[{"id":0,"characterlist":"에이해브:8","feeling":"crazy","bg":"story_depths_heart","bgm":"Bad_Time","soundeffect":"SFX_Walk_Ahab_Now, SFX_Heart_Near:loop","voice":"S503V-1091"},{"id":1,"voice":"S503V-1092"},{"id":2,"feeling":"shouting3","voice":"S503V-1093"},{"id":3,"characterlist":"이스마엘:2","feeling":"angry6","voice":"S503V-1094"},{"id":4,"feeling":"angry7","voice":"S503V-1095"},{"id":5,"feeling":"crazy","voice":"S503V-1096"},{"id":6,"feeling":"smile2","voice":"S503V-1097"},{"id":7,"feeling":"shouting","voice":"S503V-1098"},{"id":8,"voice":"S503V-1099"},{"id":9,"feeling":"smile2","voice":"S503V-1100"},{"id":10,"feeling":"shouting3","voice":"S503V-1101"},{"id":11,"feeling":"smile2","voice":"S503V-1102"},{"id":12,"voice":"S503V-1103"},{"id":13,"characterlist":"ALL:-1,이스마엘:5","feeling":"angry3_R","voice":"S503V-1104"},{"id":14,"voice":"S503V-1105"},{"id":15,"characterlist":"에이해브:5","feeling":"shouting2","soundeffect":"SFX_Sweat_Crumble_Hard","voice":"S503V-1106"},{"id":16,"voice":"S503V-1107"},{"id":17,"voice":"S503V-1107_1"},{"id":18,"voice":"S503V-1108"},{"id":19,"feeling":"crazy","voice":"S503V-1109"},{"id":20,"feeling":"shouting2","voice":"S503V-1110"},{"id":21,"feeling":"crazy","voice":"S503V-1111"},{"id":22,"feeling":"shouting2","voice":"S503V-1112"},{"id":23,"characterlist":"스타벅:2","feeling":"smile"},{"id":24},{"id":25,"characterlist":"퀴케그가면:8"},{"id":26},{"id":27,"characterlist":"ALL:-1,이스마엘:5","feeling":"sad2_R"},{"id":28,"feeling":"angry4_R","effect":"CustomCamShake:[50][7][0.5]","soundeffect":"SFX_Sweat_Crumble_Hard","voice":"S503V-1113"},{"id":29,"soundeffect":"SFX_Mace_Whip","voice":"S503V-1114"},{"id":30,"voice":"S503V-1115"},{"id":31,"characterlist":"에이해브:5","feeling":"shouting3","voice":"S503V-1116"},{"id":32,"feeling":"shouting2","effect":"CustomCamShake:[30][10][1.5]","soundeffect":"SFX_Quick_Sword_Sling","voice":"S503V-1117"}]}