{"dataList":[{"id":0,"characterlist":"데드레빗츠보스:5","feeling":"idle","bg":"story_catherine_sleep_2","bgm":"Take_Off_Your_Veil","voice":"S602V-347","effectv2":"{\"cadj\": {\"isActive\":\"true\",\"ctrl\":\"true\", \"sat\":-34}, \"overlay\": {\"isActive\":\"true\", \"ctrl\": \"true\", \"intensity\": \"1.0\", \"tex\": 0}"},{"id":1,"soundeffect":"SFX_Cloth_Rubbed_Move","voice":"S602V-348"},{"id":2},{"id":3,"characterlist":"히스클리프:5","feeling":"surprise","soundeffect":"SFX_Cotton_Crumble_SoftNew","voice":"S602V-350"},{"id":4,"characterlist":"ALL:-1,싱클레어:2","feeling":"sad","voice":"S602V-351"},{"id":5,"characterlist":"뫼르소:8","soundeffect":"SFX_ClothNCoin_Crumble","voice":"S602V-352"},{"id":6,"characterlist":"이스마엘:2","feeling":"surprise","voice":"S602V-353"},{"id":7,"voice":"S602V-354"},{"id":8,"characterlist":"ALL:-1,데드레빗츠보스:5","voice":"S602V-355"},{"id":9,"feeling":"red","soundeffect":"SFX_Jean_Crumble_Light","voice":"S602V-356"},{"id":10,"voice":"S602V-357"},{"id":11,"voice":"S602V-358"},{"id":12,"voice":"S602V-359"},{"id":13,"characterlist":"료슈:5","feeling":"idle","soundeffect":"SFX_Cloth_Rubbed_Move","voice":"S602V-360"},{"id":14,"characterlist":"파우스트:5","feeling":"idle","soundeffect":"SFX_Cotton_Crumble_SoftNew","voice":"S602V-361"},{"id":15,"characterlist":"데드레빗츠보스:5","feeling":"red","voice":"S602V-362"},{"id":16,"characterlist":"히스클리프:5","feeling":"dark2","voice":"S602V-363"},{"id":17,"feeling":"dark","voice":"S602V-364"},{"id":18,"characterlist":"데드레빗츠보스:5","feeling":"red","soundeffect":"SFX_Cotton_Crumble_SoftNew","voice":"S602V-365"},{"id":19,"characterlist":"ALL:-1","effect":"CustomCamShake:[40][9][0.3]","bgm":"Take_Off_Your_Veil:0","soundeffect":"SFX_Run_For_Attack, SFX_Grab_The_Neck:delay=0.6"},{"id":20,"characterlist":"히스클리프:5","feeling":"serious","bgm":"BGM_DestoryedLab","voice":"S602V-367"},{"id":21,"voice":"S602V-368"},{"id":22,"voice":"S602V-369"},{"id":23,"characterlist":"데드레빗츠보스:5","feeling":"red","voice":"S602V-370"},{"id":24,"characterlist":"히스클리프:5","feeling":"serious","voice":"S602V-371"},{"id":25,"feeling":"dark","soundeffect":"SFX_Stretch_HardGrab, SFX_Cloth_Rubbed_Move","voice":"S602V-372"},{"id":26,"feeling":"serious","voice":"S602V-373"},{"id":27,"characterlist":"데드레빗츠보스:5","feeling":"happy","voice":"S602V-374"},{"id":28,"feeling":"idle","bgm":"BGM_DestoryedLab:0","soundeffect":"SFX_Cotton_Crumble_SoftNew","voice":"S602V-375"},{"id":29,"characterlist":"히스클리프:5","feeling":"idle","bgm":"Lone_Wolf","voice":"S602V-376"},{"id":30,"characterlist":"데드레빗츠보스:5","voice":"S602V-377"},{"id":31,"voice":"S602V-378"},{"id":32,"feeling":"happy","soundeffect":"SFX_Cloth_Rubbed_Move","voice":"S602V-379"},{"id":33,"characterlist":"히스클리프:5","feeling":"angry","effect":"CustomCamShake:[10][20][1]","soundeffect":"SFX_Stretch_HardGrab","voice":"S602V-380"}]}